{
  "videojuegosDeSabrina": [
    {
      "titulo": "Legend of Mana",
      "genero": "RPG",
      "anio": 1999,
      "descripcion": "Juego de rol con gráficos tipo acuarela y sistema de creación de mundo."
    },
    {
      "titulo": "Little Nightmares",
      "genero": "Plataformas, Terror",
      "anio": 2017,
      "descripcion": "Una historia oscura protagonizada por Six, una niña atrapada en un lugar siniestro."
    },
    {
      "titulo": "Bendy and the Ink Machine",
      "genero": "Terror, Puzzle",
      "anio": 2017,
      "descripcion": "Un juego con estética de dibujos animados antiguos mezclado con horror psicológico."
    },
    {
      "titulo": "Overwatch",
      "genero": "Shooter, Online",
      "anio": 2016,
      "descripcion": "Shooter por equipos con héroes únicos y enfoque en el juego en equipo."
    },
    {
      "titulo": "God of War",
      "genero": "Acción, Aventura",
      "anio": 2018,
      "descripcion": "Kratos viaja con su hijo Atreus en una historia épica basada en la mitología nórdica."
    }
  ],

"videojuegosDeDamian": [
  {
    "titulo": "Mortal Kombat Ultimate",
    "plataforma": "Sega",
    "genero": "Lucha",
    "anio": 1995,
    "descripcion": "La versión definitiva del clásico juego de lucha con personajes icónicos y fatalities."
  },
  {
    "titulo": "Super Smash Bros",
    "plataforma": "Nintendo 64",
    "genero": "Lucha, Party",
    "anio": 1999,
    "descripcion": "Juego de lucha con personajes de Nintendo enfrentándose en diferentes escenarios."
  },
  {
    "titulo": "Counter Strike 1.6",
    "plataforma": "PC",
    "genero": "Shooter, Táctico",
    "anio": 2003,
    "descripcion": "Juego de disparos en primera persona con modos de juego competitivos entre terroristas y antiterroristas."
  },
  {
    "titulo": "PES",
    "plataforma": "Multiplataforma",
    "genero": "Deportes, Fútbol",
    "anio": "varios",
    "descripcion": "Popular juego de fútbol con licencias oficiales y modos de juego variados."
  },
  {
    "titulo": "Call of Duty: Modern Warfare",
    "plataforma": "Multiplataforma",
    "genero": "Shooter, Acción",
    "anio": 2019,
    "descripcion": "Shooter en primera persona con campañas intensas y modos multijugador competitivos."
  }
]
  


}
